espion_tools/__init__.py
espion_tools/espion_objects.py
espion_tools/example.py
espion_tools/exceptions.py
espion_tools/parse_espion_export.py
espion_tools/parse_mferg_export.py
espion_tools/parse_vep_export.py
espion_tools/utils.py
espion_tools-0.0.6.dist-info/METADATA
espion_tools-0.0.6.dist-info/WHEEL
espion_tools-0.0.6.dist-info/licenses/LICENSE
espion_tools-0.0.6.dist-info/RECORD
