Metadata-Version: 2.1
Name: espion_tools
Version: 0.0.6
Summary: Utility functions for reading and manipulating Espion (www.diagnosysllc.com) export files
Project-URL: Homepage, https://github.com/tomwright01/espion_tools
Project-URL: Bug Tracker, https://github.com/tomwright01/espion_tools/issues
Author-email: Tom Wright <tom@maladmin.com>
License: Copyright (c) 2022 Tom Wright, tom@maladmin.com
License-File: LICENSE
Classifier: License :: OSI Approved :: MIT License
Classifier: Operating System :: OS Independent
Classifier: Programming Language :: Python :: 3
Requires-Python: >=3.7
